allauth_jetbrains_hub
