Metadata-Version: 2.1
Name: django-allauth-jetbrains-hub
Version: 0.0.2
Summary: Jetbrains Hub OAuth2 provider for django-allauth
Home-page: https://keep.imfreedom.org/grim/django-allauth-jetbrains-hub
Author: Gary Kramlich
Author-email: grim@reaperworld.com
License: UNKNOWN
Platform: UNKNOWN
Classifier: Programming Language :: Python
Classifier: Operating System :: OS Independent
Classifier: Framework :: Django
